guard.cpython-313-darwin.so
boombox/__init__.py
boombox/boombox.py
boombox/endpoints.py
boombox/guard.c
boombox/typed.py
boombox/_vendor/pyrlang/LICENSE
boombox/_vendor/pyrlang/__init__.py
boombox/_vendor/pyrlang/errors.py
boombox/_vendor/pyrlang/match.py
boombox/_vendor/pyrlang/net_kernel.py
boombox/_vendor/pyrlang/node.py
boombox/_vendor/pyrlang/node_db.py
boombox/_vendor/pyrlang/notebook.py
boombox/_vendor/pyrlang/process.py
boombox/_vendor/pyrlang/rex.py
boombox/_vendor/pyrlang/util.py
boombox/_vendor/pyrlang/dist_proto/__init__.py
boombox/_vendor/pyrlang/dist_proto/base_dist_protocol.py
boombox/_vendor/pyrlang/dist_proto/client.py
boombox/_vendor/pyrlang/dist_proto/distribution.py
boombox/_vendor/pyrlang/dist_proto/epmd_client.py
boombox/_vendor/pyrlang/dist_proto/flags.py
boombox/_vendor/pyrlang/dist_proto/server.py
boombox/_vendor/pyrlang/dist_proto/version.py
boombox/_vendor/pyrlang/gen/__init__.py
boombox/_vendor/pyrlang/gen/decorators.py
boombox/_vendor/pyrlang/gen/server.py
boombox/_vendor/pyrlang_term-1.5a0.dist-info/licenses/LICENSE
boombox/_vendor/term/LICENSE
boombox/_vendor/term/__init__.py
boombox/_vendor/term/atom.py
boombox/_vendor/term/basetypes.py
boombox/_vendor/term/bitstring.py
boombox/_vendor/term/codec.py
boombox/_vendor/term/fun.py
boombox/_vendor/term/list.py
boombox/_vendor/term/pid.py
boombox/_vendor/term/py_codec_impl.py
boombox/_vendor/term/reference.py
boombox/_vendor/term/util.py
boombox/_vendor/term2/__init__.py
boombox/_vendor/term2/atom.py
boombox/_vendor/term2/basetypes.py
boombox/_vendor/term2/bitstring.py
boombox/_vendor/term2/codec.py
boombox/_vendor/term2/fun.py
boombox/_vendor/term2/list.py
boombox/_vendor/term2/pid.py
boombox/_vendor/term2/py_codec_impl.py
boombox/_vendor/term2/reference.py
boombox/_vendor/term2/util.py
boomboxlib-0.2.8.dist-info/licenses/LICENSE
boombox/_vendor/pyrlang_term-1.5a0.dist-info/INSTALLER
boombox/_vendor/pyrlang_term-1.5a0.dist-info/METADATA
boombox/_vendor/pyrlang_term-1.5a0.dist-info/RECORD
boombox/_vendor/pyrlang_term-1.5a0.dist-info/REQUESTED
boombox/_vendor/pyrlang_term-1.5a0.dist-info/WHEEL
boombox/_vendor/pyrlang_term-1.5a0.dist-info/direct_url.json
boombox/_vendor/pyrlang_term-1.5a0.dist-info/top_level.txt
boomboxlib-0.2.8.dist-info/METADATA
boomboxlib-0.2.8.dist-info/WHEEL
boomboxlib-0.2.8.dist-info/top_level.txt
boomboxlib-0.2.8.dist-info/RECORD
