Metadata-Version: 2.4
Name: boomboxlib
Version: 0.2.8
Summary: Boombox SDK for Python
Author: Membrane Team
License-Expression: Apache-2.0
Requires-Python: >=3.11
License-File: LICENSE
Requires-Dist: numpy>=2.2.5
Requires-Dist: typing-extensions<5,>=4.13.2
Requires-Dist: tqdm<5,>=4.67.1
Requires-Dist: platformdirs<5,>=4.4
Dynamic: license-file
